{
    "RootType": "saveMetadataContainer",
    "Data": {
        "metadata": {
            "gameDefinition": "",
            "activeQuests": "6B577A51814903CA",
            "trackedQuestEntry": "quests/meta/07_nc_underground/01_garage/00a_claire_garage",
            "trackedQuest": "LocKey#9865",
            "mainQuest": "LocKey#8554",
            "debugString": "",
            "locationName": "LocKey#10959",
            "playerPosition": {
                "X": -567.192138671875,
                "Y": -870.5665893554688,
                "Z": 7.850250244140625
            },
            "playTime": 49562.2573404,
            "playthroughTime": 55012.0669436,
            "nextSavableEntityID": 9007473,
            "nextNonSavableEntityID": 10089621,
            "lifePath": "StreetKid",
            "bodyGender": "Male",
            "brainGender": "Male",
            "level": 13.0,
            "streetCred": 16.0,
            "gunslinger": 2.0,
            "assault": 5.0,
            "demolition": 2.0,
            "athletics": 6.0,
            "brawling": 1.0,
            "coldBlood": 2.0,
            "stealth": 3.0,
            "engineering": 3.0,
            "crafting": 3.0,
            "hacking": 3.0,
            "combatHacking": 1.0,
            "strength": 6.0,
            "intelligence": 3.0,
            "reflexes": 5.0,
            "technicalAbility": 5.0,
            "cool": 3.0,
            "initialBuildID": "3.0.3206637  P4CL: 4147542  Stream: //R6.Root/R6.Main.BuildAgent ",
            "finishedQuests": "q004 q005 q000 q001 q003 q105 q101 sq018 ma_hey_spr_12 ma_wat_nid_27 ",
            "playthroughID": "5fdb3a15158a7a68",
            "pointOfNoReturnId": "",
            "visitID": "65bb483b-8dfa-44d9-8cba-788ed00ba3bf",
            "buildSKU": "",
            "buildPatch": "1.02",
            "difficulty": "Easy",
            "saveVersion": 193,
            "gameVersion": 6,
            "timestampString": "17:25:15, 25.12.2020",
            "name": "AutoSave-1",
            "userName": "",
            "buildID": "3.0.3206637  P4CL: 4147542  Stream: //R6.Root/R6.Main.BuildAgent ",
            "platform": "pc",
            "censorFlags": "",
            "buildConfiguration": "final",
            "fileSize": 2943218,
            "isForced": false,
            "isCheckpoint": false,
            "initialLoadingScreenID": 183640721353,
            "isStoryMode": false,
            "isPointOfNoReturn": false,
            "isEndGameSave": false
        }
    }
}